{
  "description": "예시 지식 데이터 - API의 /knowledge/bulk 엔드포인트로 등록하세요",
  "entries": [
    {
      "category": "strategy",
      "title": "가치 투자 원칙",
      "content": "PER 10 이하, PBR 1 이하인 종목 중 영업이익이 3년 연속 성장하는 기업을 우선 검토한다. 시가총액 대비 현금보유 비율이 30% 이상이면 안전마진이 있다고 판단한다.",
      "tags": ["가치투자", "PER", "PBR", "안전마진"]
    },
    {
      "category": "indicator",
      "title": "골든크로스/데드크로스 전략",
      "content": "5일 이동평균선이 20일 이동평균선을 상향 돌파(골든크로스)하면 매수 신호, 하향 돌파(데드크로스)하면 매도 신호로 본다. 단, 거래량이 평균 대비 150% 이상 동반되어야 유효한 신호로 판단한다.",
      "tags": ["이동평균", "골든크로스", "데드크로스", "기술적분석"]
    },
    {
      "category": "rule",
      "title": "손절/익절 규칙",
      "content": "매수가 대비 -7% 도달 시 무조건 손절한다. 목표가 도달 시 50%를 익절하고 나머지는 트레일링 스탑(-5%)으로 관리한다. 감정적 매매를 절대 하지 않는다.",
      "tags": ["손절", "익절", "리스크관리", "매매규칙"]
    },
    {
      "category": "sector",
      "title": "반도체 섹터 분석 기준",
      "content": "반도체 섹터는 메모리(DRAM/NAND) 가격 사이클을 최우선으로 확인한다. ASP 상승 전환 시점에서 관련 종목(삼성전자, SK하이닉스)에 비중을 늘린다. 파운드리 수주 동향과 AI 수요도 핵심 변수다.",
      "tags": ["반도체", "메모리", "삼성전자", "SK하이닉스", "AI"]
    },
    {
      "category": "pattern",
      "title": "실적 시즌 패턴",
      "content": "한국 기업의 실적 발표는 1월, 4월, 7월, 10월에 집중된다. 실적 발표 2주 전부터 컨센서스 대비 서프라이즈 가능성이 높은 종목을 선별한다. 어닝 서프라이즈 후 3일 이내 추가 상승 확률이 높다.",
      "tags": ["실적시즌", "어닝서프라이즈", "계절성"]
    }
  ]
}
